metafitch/__init__.py
metafitch/_version.py
metafitch/cli.py
metafitch/get_num_descendants.py
metafitch/metafitch.py
metafitch-0.0.3.dist-info/METADATA
metafitch-0.0.3.dist-info/WHEEL
metafitch-0.0.3.dist-info/entry_points.txt
metafitch-0.0.3.dist-info/top_level.txt
metafitch-0.0.3.dist-info/RECORD
