Metadata-Version: 2.1
Name: metafitch
Version: 0.0.3
Summary: "Metadata ancestral state reconstruction by Fitch's method"
Home-page: https://github.com/theosanderson/chronumental
Author: Theo Sanderson
Author-email: theo@theo.io
Project-URL: Bug Tracker, https://github.com/theosanderson/chronumental/issues
Classifier: Programming Language :: Python :: 3
Classifier: License :: OSI Approved :: MIT License
Classifier: Operating System :: OS Independent
Requires-Python: >=3.6
Requires-Dist: alive-progress
Requires-Dist: pandas
Requires-Dist: treeswift
Requires-Dist: xopen
